Metadata-Version: 1.0
Name: weblele
Version: 0.0.1.dev0
Summary: create web site
Home-page: http://katolele.net/
Author: katolele
Author-email: katolele@katolele.net
License: GPL
Platform: UNKNOWN
